xinstall/__init__.py
xinstall/ai.py
xinstall/bigdata.py
xinstall/data/SpaceVim/SpaceVim/init.vim
xinstall/data/SpaceVim/SpaceVim.d/init.toml
xinstall/data/SpaceVim/SpaceVim.d/vimrc
xinstall/data/chrome/vimium/conf.txt
xinstall/data/cygwin/cygwin.bat
xinstall/data/cygwin/profile.sh
xinstall/data/darglint/darglint
xinstall/data/eclipse/dictionary.txt
xinstall/data/firefox/noscripts/config/config.txt
xinstall/data/firefox/noscripts/whitelist/whitelist.txt
xinstall/data/firefox/prefs.js
xinstall/data/firefox/profiles.ini
xinstall/data/flake8/flake8
xinstall/data/geany/colorschemes/bespin.conf
xinstall/data/geany/colorschemes/black.conf
xinstall/data/geany/colorschemes/dark-fruit-salad.conf
xinstall/data/geany/colorschemes/dark.conf
xinstall/data/geany/colorschemes/fluffy.conf
xinstall/data/geany/colorschemes/gedit.conf
xinstall/data/geany/colorschemes/github.conf
xinstall/data/geany/colorschemes/inkpot.conf
xinstall/data/geany/colorschemes/kugel.conf
xinstall/data/geany/colorschemes/mc.conf
xinstall/data/geany/colorschemes/monokai.conf
xinstall/data/geany/colorschemes/oblivion2.conf
xinstall/data/geany/colorschemes/pygments.conf
xinstall/data/geany/colorschemes/railcasts2.conf
xinstall/data/geany/colorschemes/retro.conf
xinstall/data/geany/colorschemes/slushpoppies.conf
xinstall/data/geany/colorschemes/solarized-dark.conf
xinstall/data/geany/colorschemes/solarized-light.conf
xinstall/data/geany/colorschemes/steampunk.conf
xinstall/data/geany/colorschemes/tango-dark.conf
xinstall/data/geany/colorschemes/tango-light.conf
xinstall/data/geany/colorschemes/tinge.conf
xinstall/data/geany/colorschemes/ubuntu.conf
xinstall/data/geany/colorschemes/vibrant-ink.conf
xinstall/data/geany/colorschemes/zenburn.conf
xinstall/data/geany/filedefs/filetypes.README
xinstall/data/geany/geany.conf
xinstall/data/geany/keybindings.conf
xinstall/data/geany/templates/templates.README
xinstall/data/git/gitconfig
xinstall/data/git/gitignore_java
xinstall/data/git/gitignore_python
xinstall-0.52.2.dist-info/entry_points.txt
xinstall-0.52.2.dist-info/LICENSE
xinstall-0.52.2.dist-info/WHEEL
xinstall-0.52.2.dist-info/METADATA
xinstall-0.52.2.dist-info/RECORD
