Metadata-Version: 2.1
Name: xinstall
Version: 0.52.2
Summary: Easy Cross-platform Installation and Configuration of Apps.
Home-page: https://github.com/legendu-net/xinstall
License: MIT
Keywords: installation,configuration,cross-platform
Author: Benjamin Du
Author-email: longendu@yahoo.com
Requires-Python: >=3.7.1,<4
Classifier: License :: OSI Approved :: MIT License
Classifier: Programming Language :: Python :: 3
Classifier: Programming Language :: Python :: 3.10
Classifier: Programming Language :: Python :: 3.8
Classifier: Programming Language :: Python :: 3.9
Requires-Dist: distro (>=1.5.0)
Requires-Dist: findspark (>=1.4.2)
Requires-Dist: packaging (>=20.4)
Requires-Dist: requests (>=2.25.0)
Requires-Dist: tomlkit (>=0.7.0)
Requires-Dist: tqdm (>=4.48.2)
Project-URL: Repository, https://github.com/legendu-net/xinstall
